[
  {
    "id": 1,
    "airline": "Delta Airlines",
    "flightNumber": "DL123",
    "departure": "JFK",
    "arrival": "LAX",
    "departureTime": "2023-06-15T08:00:00",
    "arrivalTime": "2023-06-15T11:00:00",
    "price": 299,
    "duration": "3h 0m",
    "stops": 0,
    "image": "/images/delta-airlines.jpg",
    "aircraft": "Boeing 737-800",
    "seatsAvailable": 24,
    "baggageAllowance": "1 checked bag (23kg) + 1 carry-on",
    "amenities": ["WiFi", "Entertainment", "Meal", "USB Charging"],
    "departureTerminal": "Terminal 4",
    "arrivalTerminal": "Terminal 5",
    "airlineLogo": "/images/delta-logo.png"
  },
  {
    "id": 2,
    "airline": "United Airlines",
    "flightNumber": "UA456",
    "departure": "ORD",
    "arrival": "SFO",
    "departureTime": "2023-06-15T10:30:00",
    "arrivalTime": "2023-06-15T13:15:00",
    "price": 349,
    "duration": "2h 45m",
    "stops": 0,
    "image": "/images/united-airlines.jpg",
    "aircraft": "Airbus A320",
    "seatsAvailable": 12,
    "baggageAllowance": "1 checked bag (23kg) + 1 carry-on",
    "amenities": ["WiFi", "Entertainment", "USB Charging"],
    "departureTerminal": "Terminal 1",
    "arrivalTerminal": "Terminal 3",
    "airlineLogo": "/images/united-logo.png"
  },
  {
    "id": 3,
    "airline": "American Airlines",
    "flightNumber": "AA789",
    "departure": "DFW",
    "arrival": "MIA",
    "departureTime": "2023-06-15T14:00:00",
    "arrivalTime": "2023-06-15T17:30:00",
    "price": 199,
    "duration": "3h 30m",
    "stops": 1,
    "image": "/images/american-airlines.jpg",
    "aircraft": "Boeing 787",
    "seatsAvailable": 8,
    "baggageAllowance": "1 checked bag (23kg)",
    "amenities": ["WiFi", "Meal", "USB Charging"],
    "departureTerminal": "Terminal B",
    "arrivalTerminal": "Terminal D",
    "airlineLogo": "/images/american-logo.png"
  },
  {
    "id": 4,
    "airline": "Southwest Airlines",
    "flightNumber": "WN321",
    "departure": "DEN",
    "arrival": "LAS",
    "departureTime": "2023-06-15T16:45:00",
    "arrivalTime": "2023-06-15T18:15:00",
    "price": 129,
    "duration": "1h 30m",
    "stops": 0,
    "image": "/images/southwest-airlines.jpg",
    "aircraft": "Boeing 737-700",
    "seatsAvailable": 32,
    "baggageAllowance": "2 checked bags (23kg each) + 1 carry-on",
    "amenities": ["WiFi"],
    "departureTerminal": "Terminal C",
    "arrivalTerminal": "Terminal 1",
    "airlineLogo": "/images/southwest-logo.png"
  },
  {
    "id": 5,
    "airline": "JetBlue",
    "flightNumber": "B6543",
    "departure": "BOS",
    "arrival": "JFK",
    "departureTime": "2023-06-15T19:00:00",
    "arrivalTime": "2023-06-15T20:30:00",
    "price": 159,
    "duration": "1h 30m",
    "stops": 0,
    "image": "/images/jetblue-airlines.jpg",
    "aircraft": "Airbus A321",
    "seatsAvailable": 18,
    "baggageAllowance": "1 checked bag (23kg) + 1 carry-on",
    "amenities": ["WiFi", "Entertainment", "Snack", "USB Charging"],
    "departureTerminal": "Terminal A",
    "arrivalTerminal": "Terminal 5",
    "airlineLogo": "/images/jetblue-logo.png"
  }
]